remote_mcp_scanner/__init__.py
remote_mcp_scanner/cli.py
remote_mcp_scanner/scanner.py
remote_mcp_scanner/utils/__init__.py
remote_mcp_scanner/utils/colors.py
remote_mcp_scanner/utils/http.py
remote_mcp_scanner-1.0.0.dist-info/licenses/LICENSE
remote_mcp_scanner-1.0.0.dist-info/METADATA
remote_mcp_scanner-1.0.0.dist-info/WHEEL
remote_mcp_scanner-1.0.0.dist-info/entry_points.txt
remote_mcp_scanner-1.0.0.dist-info/top_level.txt
remote_mcp_scanner-1.0.0.dist-info/RECORD
