Metadata-Version: 2.4
Name: remote-mcp-scanner
Version: 1.0.0
Summary: A security scanner for remote MCP (Model Context Protocol) servers
Home-page: https://github.com/novasecuritynz/remote-mcp-scanner
Author: Nova Security
Author-email: Nova Security <info@novasecurity.co.nz>
License: MIT
Project-URL: Homepage, https://github.com/novasecuritynz/remote-mcp-scanner
Project-URL: Bug Reports, https://github.com/novasecuritynz/remote-mcp-scanner/issues
Project-URL: Source, https://github.com/novasecuritynz/remote-mcp-scanner
Project-URL: Documentation, https://github.com/novasecuritynz/remote-mcp-scanner#readme
Keywords: security,oauth,mcp,scanner,vulnerability,xss,penetration-testing
Classifier: Development Status :: 4 - Beta
Classifier: Intended Audience :: Developers
Classifier: Intended Audience :: Information Technology
Classifier: Topic :: Security
Classifier: Topic :: Software Development :: Testing
Classifier: License :: OSI Approved :: MIT License
Classifier: Programming Language :: Python :: 3
Classifier: Programming Language :: Python :: 3.8
Classifier: Programming Language :: Python :: 3.9
Classifier: Programming Language :: Python :: 3.10
Classifier: Programming Language :: Python :: 3.11
Classifier: Programming Language :: Python :: 3.12
Classifier: Operating System :: OS Independent
Requires-Python: >=3.8
License-File: LICENSE
Requires-Dist: httpx
Requires-Dist: click
Requires-Dist: beautifulsoup4
Dynamic: author
Dynamic: home-page
Dynamic: license-file
Dynamic: requires-python
